brahm_centre_utils/__init__.py
brahm_centre_utils/common/__init__.py
brahm_centre_utils/common/common_utils.py
brahm_centre_utils/data_cleaning/__init__.py
brahm_centre_utils/data_cleaning/clear_duplicates.py
brahm_centre_utils/onemap/__init__.py
brahm_centre_utils/onemap/onemap_handler.py
brahm_centre_utils/salesforce/__init__.py
brahm_centre_utils/salesforce/salesforce_handler.py
common/__init__.py
common/common_utils.py
data_cleaning/__init__.py
data_cleaning/clear_duplicates.py
onemap/__init__.py
onemap/onemap_handler.py
salesforce/__init__.py
salesforce/salesforce_handler.py
brahm_centre_utils-1.0.5.dist-info/METADATA
brahm_centre_utils-1.0.5.dist-info/WHEEL
brahm_centre_utils-1.0.5.dist-info/top_level.txt
brahm_centre_utils-1.0.5.dist-info/RECORD
