Metadata-Version: 2.1
Name: brahm_centre_utils
Version: 1.0.5
Summary: Brahm Centre internal utility functions
Home-page: https://github.com/Brahm-Centre-SG/bc-utils-package
Author: Nguyen An Khanh
Author-email: ankhanh@brahmcentre.com
Requires-Dist: pandas
